classifier_model/VERSION
classifier_model/__init__.py
classifier_model/config.yml
classifier_model/pipeline.py
classifier_model/predict.py
classifier_model/train_pipeline.py
classifier_model/config/__init__.py
classifier_model/config/core.py
classifier_model/dataset/__init__.py
classifier_model/dataset/test.csv
classifier_model/dataset/train.csv
classifier_model/models/__init__.py
classifier_model/models/spaceship_titanic_pipeline_model_output_v1.0.9.pkl
classifier_model/preprocessing/__init__.py
classifier_model/preprocessing/data_manager.py
classifier_model/preprocessing/data_validation.py
classifier_model/preprocessing/features.py
tests/__init__.py
tests/conftest.py
tests/test_config.py
tests/test_features.py
tests/test_predict.py
spaceship_titanic_classif_model-1.0.9.dist-info/LICENSE
spaceship_titanic_classif_model-1.0.9.dist-info/METADATA
spaceship_titanic_classif_model-1.0.9.dist-info/WHEEL
spaceship_titanic_classif_model-1.0.9.dist-info/top_level.txt
spaceship_titanic_classif_model-1.0.9.dist-info/RECORD
